feature_utils/__init__.py
feature_utils/transformers.py
feature_utils/version.py
feature_utils/imports/basic_imports.py
feature_utils/utils/transformer_utils.py
feature_utils-0.1b0.dist-info/LICENCE
feature_utils-0.1b0.dist-info/METADATA
feature_utils-0.1b0.dist-info/WHEEL
feature_utils-0.1b0.dist-info/top_level.txt
feature_utils-0.1b0.dist-info/RECORD
